Liege
