Metadata-Version: 2.1
Name: Liege.urban.dataimport
Version: 0.1.2
Summary: liege urban dataimport
Home-page: http://pypi.python.org/pypi/Liege.urban.dataimport
Author: IMIO
Author-email: dev@imio.be
License: GPL
Keywords: Python Zope Plone
Classifier: Environment :: Web Environment
Classifier: Framework :: Plone :: 4.3
Classifier: Programming Language :: Python :: 2.7
Provides-Extra: test
Provides-Extra: develop
